setup.py
renal/__init__.py
renal/version.py
renal.egg-info/PKG-INFO
renal.egg-info/SOURCES.txt
renal.egg-info/dependency_links.txt
renal.egg-info/entry_points.txt
renal.egg-info/top_level.txt